setup.py
HOTBot.egg-info/PKG-INFO
HOTBot.egg-info/SOURCES.txt
HOTBot.egg-info/dependency_links.txt
HOTBot.egg-info/entry_points.txt
HOTBot.egg-info/pbr.json
HOTBot.egg-info/requires.txt
HOTBot.egg-info/top_level.txt
hotbot/__init__.py
hotbot/jsonconf.py