Metadata-Version: 1.1
Name: HOTBot
Version: 1.0.1
Summary: Dynamic, random, and automated event scheduler using Google Calendar
Home-page: https://github.com/adammhaile/HotBot
Author: Adam Haile
Author-email: email@adamhaile.net
License: MIT
Platform: UNKNOWN
Classifier: Development Status :: 5 - Production/Stable
Classifier: License :: OSI Approved :: MIT License
Classifier: Programming Language :: Python :: 2
Classifier: Programming Language :: Python :: 2.6
Classifier: Programming Language :: Python :: 2.7
